asone/__init__.py
asone/asone.py
asone/demo_detector.py
asone/demo_ocr.py
asone/demo_pose_estimator.py
asone/demo_segmentor.py
asone/demo_tracker.py
asone/pose_estimator.py
asone/detectors/__init__.py
asone/detectors/detector.py
asone/detectors/easyocr_detector/__init__.py
asone/detectors/easyocr_detector/text_detector.py
asone/detectors/utils/__init__.py
asone/detectors/utils/cfg_path.py
asone/detectors/utils/coreml_utils.py
asone/detectors/utils/exp_name.py
asone/detectors/utils/weights_path.py
asone/detectors/yolonas/__init__.py
asone/detectors/yolonas/yolonas.py
asone/detectors/yolor/__init__.py
asone/detectors/yolor/yolor_detector.py
asone/detectors/yolor/cfg/yolor_csp.cfg
asone/detectors/yolor/cfg/yolor_csp_x.cfg
asone/detectors/yolor/cfg/yolor_p6.cfg
asone/detectors/yolor/models/__init__.py
asone/detectors/yolor/models/common.py
asone/detectors/yolor/models/export.py
asone/detectors/yolor/models/models.py
asone/detectors/yolor/utils/__init__.py
asone/detectors/yolor/utils/activations.py
asone/detectors/yolor/utils/autoanchor.py
asone/detectors/yolor/utils/datasets.py
asone/detectors/yolor/utils/export.py
asone/detectors/yolor/utils/general.py
asone/detectors/yolor/utils/google_utils.py
asone/detectors/yolor/utils/layers.py
asone/detectors/yolor/utils/loss.py
asone/detectors/yolor/utils/metrics.py
asone/detectors/yolor/utils/parse_config.py
asone/detectors/yolor/utils/plots.py
asone/detectors/yolor/utils/torch_utils.py
asone/detectors/yolor/utils/yolor_utils.py
asone/detectors/yolov5/__init__.py
asone/detectors/yolov5/yolov5_detector.py
asone/detectors/yolov5/yolov5/__init__.py
asone/detectors/yolov5/yolov5/export.py
asone/detectors/yolov5/yolov5/models/__init__.py
asone/detectors/yolov5/yolov5/models/common.py
asone/detectors/yolov5/yolov5/models/experimental.py
asone/detectors/yolov5/yolov5/models/general.py
asone/detectors/yolov5/yolov5/models/tf.py
asone/detectors/yolov5/yolov5/models/yolo.py
asone/detectors/yolov5/yolov5/utils/__init__.py
asone-2.0.0.dist-info/LICENCE
asone-2.0.0.dist-info/METADATA
asone-2.0.0.dist-info/WHEEL
asone-2.0.0.dist-info/dependency_links.txt
asone-2.0.0.dist-info/top_level.txt
asone-2.0.0.dist-info/RECORD
