Metadata-Version: 2.1
Name: asone
Version: 2.0.0
Summary: UNKNOWN
Home-page: https://github.com/augmentedstartups/AS-One
Author: AxcelerateAI
Author-email: dev@axcelerate.ai
License: BSD 2-clause
Keywords: asone bytetrack deepsort norfair yolo yolox yolor yolov5 yolov7 yolov8 yolov9 sam segment-anything installation inferencing
Platform: UNKNOWN
Classifier: Development Status :: 1 - Planning
Classifier: Intended Audience :: Science/Research
Classifier: License :: OSI Approved :: MIT License
Classifier: Operating System :: POSIX :: Linux
Classifier: Operating System :: Microsoft :: Windows :: Windows 10
Classifier: Programming Language :: Python :: 3
Classifier: Programming Language :: Python :: 3.8
Classifier: Programming Language :: Python :: 3.9
Classifier: Programming Language :: Python :: 3.10
Requires-Dist: Cython (==3.0.9)
Requires-Dist: IPython
Requires-Dist: asone-ocr
Requires-Dist: coremltools
Requires-Dist: cython-bbox
Requires-Dist: easydict
Requires-Dist: gdown
Requires-Dist: lap
Requires-Dist: loguru
Requires-Dist: motpy
Requires-Dist: norfair
Requires-Dist: numpy (==1.23.3)
Requires-Dist: onnxruntime
Requires-Dist: opencv-python
Requires-Dist: pandas
Requires-Dist: pillow (==9.5.0)
Requires-Dist: protobuf (==3.20.*)
Requires-Dist: pyyaml
Requires-Dist: scipy
Requires-Dist: segment-anything
Requires-Dist: super-gradients
Requires-Dist: tabulate
Requires-Dist: tensorboard
Requires-Dist: thop
Requires-Dist: torch
Requires-Dist: torchreid (==0.2.5)
Requires-Dist: torchvision
Requires-Dist: typing-extensions
Requires-Dist: ultralytics (==8.1.30)
Requires-Dist: wheel
